graplinc/grapl/api/__init__.py
graplinc/grapl/api/graph/__init__.py
graplinc/grapl/api/graph/v1beta1/__init__.py
graplinc/grapl/api/graph/v1beta1/types_pb2.py
graplinc_grapl_api-0.1.0.dist-info/METADATA
graplinc_grapl_api-0.1.0.dist-info/WHEEL
graplinc_grapl_api-0.1.0.dist-info/namespace_packages.txt
graplinc_grapl_api-0.1.0.dist-info/top_level.txt
graplinc_grapl_api-0.1.0.dist-info/RECORD
